{
  "projectRoot": "/dev/software_evo/Series-2/clone-demo",
  "clones": [
    {
      "locations": [
        {
          "filePath": "src/main/java/com/example/combat/BattleSimulator.java",
          "startLine": 61,
          "endLine": 67
        },
        {
          "filePath": "src/main/java/com/example/combat/BattleSimulator.java",
          "startLine": 67,
          "endLine": 73
        }
      ],
      "fragmentLength": 7,
      "cloneType": 3,
      "_id": "block([declarationStatement(variables([],simpleType(id(\"TYPE\")),[variable(id(\"ID\"),[],methodCall(id(\"ID\"),[],id(\"ID\"),[]))])),expressionStatement(methodCall(id(\"ID\"),[],id(\"ID\"),[plus(stringLiteral(\"STR\"),methodCall(id(\"ID\"),[],id(\"ID\"),[]))])),expressionStatement(methodCall(id(\"ID\"),[],id(\"ID\"),[methodCall(id(\"ID\"),[],id(\"ID\"),[]),stringLiteral(\"STR\"),stringLiteral(\"STR\")])),expressionStatement(methodCall(id(\"ID\"),[],id(\"ID\"),[])),expressionStatement(methodCall(id(\"ID\"),[],id(\"ID\"),[id(\"ID\")]))])-61-67",
      "name": "ASTClone_61_67"
    },
    {
      "locations": [
        {
          "filePath": "src/main/java/com/example/combat/BattleSimulator.java",
          "startLine": 61,
          "endLine": 67
        },
        {
          "filePath": "src/main/java/com/example/combat/BattleSimulator.java",
          "startLine": 75,
          "endLine": 82
        }
      ],
      "fragmentLength": 7,
      "cloneType": 3,
      "_id": "block([declarationStatement(variables([],simpleType(id(\"TYPE\")),[variable(id(\"ID\"),[],methodCall(id(\"ID\"),[],id(\"ID\"),[]))])),expressionStatement(methodCall(id(\"ID\"),[],id(\"ID\"),[plus(stringLiteral(\"STR\"),methodCall(id(\"ID\"),[],id(\"ID\"),[]))])),expressionStatement(methodCall(id(\"ID\"),[],id(\"ID\"),[methodCall(id(\"ID\"),[],id(\"ID\"),[]),stringLiteral(\"STR\"),stringLiteral(\"STR\")])),expressionStatement(methodCall(id(\"ID\"),[],id(\"ID\"),[])),expressionStatement(methodCall(id(\"ID\"),[],id(\"ID\"),[id(\"ID\")]))])-61-75",
      "name": "ASTClone_61_75"
    },
    {
      "locations": [
        {
          "filePath": "src/main/java/com/example/ui/BattlePanel.java",
          "startLine": 103,
          "endLine": 109
        },
        {
          "filePath": "src/main/java/com/example/ui/BattlePanel.java",
          "startLine": 111,
          "endLine": 117
        }
      ],
      "fragmentLength": 7,
      "cloneType": 3,
      "_id": "if(notEquals(id(\"ID\"),null()),block([expressionStatement(methodCall(id(\"ID\"),[],id(\"ID\"),[id(\"ID\"),number(\"LIT\"),id(\"ID\"),id(\"ID\"),id(\"ID\"),this()]))]),block([expressionStatement(methodCall(id(\"ID\"),[],id(\"ID\"),[qualifiedName([id(\"ID\"),id(\"ID\")])])),expressionStatement(methodCall(id(\"ID\"),[],id(\"ID\"),[number(\"LIT\"),id(\"ID\"),id(\"ID\"),id(\"ID\")])),expressionStatement(methodCall(id(\"ID\"),[],id(\"ID\"),[qualifiedName([id(\"ID\"),id(\"ID\")])])),expressionStatement(methodCall(id(\"ID\"),[],id(\"ID\"),[stringLiteral(\"STR\"),number(\"LIT\"),plus(id(\"ID\"),number(\"LIT\"))]))]))-103-111",
      "name": "ASTClone_103_111"
    },
    {
      "locations": [
        {
          "filePath": "src/main/java/com/example/ui/BattlePanel.java",
          "startLine": 103,
          "endLine": 109
        },
        {
          "filePath": "src/main/java/com/example/ui/BattlePanel.java",
          "startLine": 119,
          "endLine": 125
        }
      ],
      "fragmentLength": 7,
      "cloneType": 3,
      "_id": "if(notEquals(id(\"ID\"),null()),block([expressionStatement(methodCall(id(\"ID\"),[],id(\"ID\"),[id(\"ID\"),number(\"LIT\"),id(\"ID\"),id(\"ID\"),id(\"ID\"),this()]))]),block([expressionStatement(methodCall(id(\"ID\"),[],id(\"ID\"),[qualifiedName([id(\"ID\"),id(\"ID\")])])),expressionStatement(methodCall(id(\"ID\"),[],id(\"ID\"),[number(\"LIT\"),id(\"ID\"),id(\"ID\"),id(\"ID\")])),expressionStatement(methodCall(id(\"ID\"),[],id(\"ID\"),[qualifiedName([id(\"ID\"),id(\"ID\")])])),expressionStatement(methodCall(id(\"ID\"),[],id(\"ID\"),[stringLiteral(\"STR\"),number(\"LIT\"),plus(id(\"ID\"),number(\"LIT\"))]))]))-103-119",
      "name": "ASTClone_103_119"
    },
    {
      "locations": [
        {
          "filePath": "src/main/java/com/example/ui/BattlePanel.java",
          "startLine": 103,
          "endLine": 109
        },
        {
          "filePath": "src/main/java/com/example/ui/BattlePanel.java",
          "startLine": 127,
          "endLine": 134
        }
      ],
      "fragmentLength": 7,
      "cloneType": 3,
      "_id": "if(notEquals(id(\"ID\"),null()),block([expressionStatement(methodCall(id(\"ID\"),[],id(\"ID\"),[id(\"ID\"),number(\"LIT\"),id(\"ID\"),id(\"ID\"),id(\"ID\"),this()]))]),block([expressionStatement(methodCall(id(\"ID\"),[],id(\"ID\"),[qualifiedName([id(\"ID\"),id(\"ID\")])])),expressionStatement(methodCall(id(\"ID\"),[],id(\"ID\"),[number(\"LIT\"),id(\"ID\"),id(\"ID\"),id(\"ID\")])),expressionStatement(methodCall(id(\"ID\"),[],id(\"ID\"),[qualifiedName([id(\"ID\"),id(\"ID\")])])),expressionStatement(methodCall(id(\"ID\"),[],id(\"ID\"),[stringLiteral(\"STR\"),number(\"LIT\"),plus(id(\"ID\"),number(\"LIT\"))]))]))-103-127",
      "name": "ASTClone_103_127"
    },
    {
      "locations": [
        {
          "filePath": "src/main/java/com/example/ui/BattlePanel.java",
          "startLine": 111,
          "endLine": 117
        },
        {
          "filePath": "src/main/java/com/example/ui/BattlePanel.java",
          "startLine": 119,
          "endLine": 125
        }
      ],
      "fragmentLength": 7,
      "cloneType": 3,
      "_id": "if(notEquals(id(\"ID\"),null()),block([expressionStatement(methodCall(id(\"ID\"),[],id(\"ID\"),[id(\"ID\"),number(\"LIT\"),id(\"ID\"),id(\"ID\"),id(\"ID\"),this()]))]),block([expressionStatement(methodCall(id(\"ID\"),[],id(\"ID\"),[qualifiedName([id(\"ID\"),id(\"ID\")])])),expressionStatement(methodCall(id(\"ID\"),[],id(\"ID\"),[number(\"LIT\"),id(\"ID\"),id(\"ID\"),id(\"ID\")])),expressionStatement(methodCall(id(\"ID\"),[],id(\"ID\"),[qualifiedName([id(\"ID\"),id(\"ID\")])])),expressionStatement(methodCall(id(\"ID\"),[],id(\"ID\"),[stringLiteral(\"STR\"),number(\"LIT\"),plus(id(\"ID\"),number(\"LIT\"))]))]))-111-119",
      "name": "ASTClone_111_119"
    },
    {
      "locations": [
        {
          "filePath": "src/main/java/com/example/ui/BattlePanel.java",
          "startLine": 111,
          "endLine": 117
        },
        {
          "filePath": "src/main/java/com/example/ui/BattlePanel.java",
          "startLine": 127,
          "endLine": 134
        }
      ],
      "fragmentLength": 7,
      "cloneType": 3,
      "_id": "if(notEquals(id(\"ID\"),null()),block([expressionStatement(methodCall(id(\"ID\"),[],id(\"ID\"),[id(\"ID\"),number(\"LIT\"),id(\"ID\"),id(\"ID\"),id(\"ID\"),this()]))]),block([expressionStatement(methodCall(id(\"ID\"),[],id(\"ID\"),[qualifiedName([id(\"ID\"),id(\"ID\")])])),expressionStatement(methodCall(id(\"ID\"),[],id(\"ID\"),[number(\"LIT\"),id(\"ID\"),id(\"ID\"),id(\"ID\")])),expressionStatement(methodCall(id(\"ID\"),[],id(\"ID\"),[qualifiedName([id(\"ID\"),id(\"ID\")])])),expressionStatement(methodCall(id(\"ID\"),[],id(\"ID\"),[stringLiteral(\"STR\"),number(\"LIT\"),plus(id(\"ID\"),number(\"LIT\"))]))]))-111-127",
      "name": "ASTClone_111_127"
    },
    {
      "locations": [
        {
          "filePath": "src/main/java/com/example/ui/BattlePanel.java",
          "startLine": 119,
          "endLine": 125
        },
        {
          "filePath": "src/main/java/com/example/ui/BattlePanel.java",
          "startLine": 127,
          "endLine": 134
        }
      ],
      "fragmentLength": 7,
      "cloneType": 3,
      "_id": "if(notEquals(id(\"ID\"),null()),block([expressionStatement(methodCall(id(\"ID\"),[],id(\"ID\"),[id(\"ID\"),number(\"LIT\"),id(\"ID\"),id(\"ID\"),id(\"ID\"),this()]))]),block([expressionStatement(methodCall(id(\"ID\"),[],id(\"ID\"),[qualifiedName([id(\"ID\"),id(\"ID\")])])),expressionStatement(methodCall(id(\"ID\"),[],id(\"ID\"),[number(\"LIT\"),id(\"ID\"),id(\"ID\"),id(\"ID\")])),expressionStatement(methodCall(id(\"ID\"),[],id(\"ID\"),[qualifiedName([id(\"ID\"),id(\"ID\")])])),expressionStatement(methodCall(id(\"ID\"),[],id(\"ID\"),[stringLiteral(\"STR\"),number(\"LIT\"),plus(id(\"ID\"),number(\"LIT\"))]))]))-119-127",
      "name": "ASTClone_119_127"
    },
    {
      "locations": [
        {
          "filePath": "src/main/java/com/example/combat/BattleSimulator.java",
          "startLine": 67,
          "endLine": 73
        },
        {
          "filePath": "src/main/java/com/example/combat/BattleSimulator.java",
          "startLine": 75,
          "endLine": 82
        }
      ],
      "fragmentLength": 7,
      "cloneType": 3,
      "_id": "if(greater(methodCall(id(\"ID\"),[],id(\"ID\"),[]),number(\"LIT\")),block([declarationStatement(variables([],simpleType(id(\"TYPE\")),[variable(id(\"ID\"),[],methodCall(id(\"ID\"),[],id(\"ID\"),[]))])),expressionStatement(methodCall(id(\"ID\"),[],id(\"ID\"),[plus(stringLiteral(\"STR\"),methodCall(id(\"ID\"),[],id(\"ID\"),[]))])),expressionStatement(methodCall(id(\"ID\"),[],id(\"ID\"),[methodCall(id(\"ID\"),[],id(\"ID\"),[]),stringLiteral(\"STR\"),stringLiteral(\"STR\")])),expressionStatement(methodCall(id(\"ID\"),[],id(\"ID\"),[])),expressionStatement(methodCall(id(\"ID\"),[],id(\"ID\"),[id(\"ID\")]))]))-67-75",
      "name": "ASTClone_67_75"
    },
    {
      "locations": [
        {
          "filePath": "src/main/java/com/example/combat/BattleSimulator.java",
          "startLine": 100,
          "endLine": 107
        },
        {
          "filePath": "src/main/java/com/example/combat/BattleSimulator.java",
          "startLine": 109,
          "endLine": 115
        }
      ],
      "fragmentLength": 8,
      "cloneType": 3,
      "_id": "if(lessEquals(methodCall(id(\"ID\"),[],id(\"ID\"),[]),number(\"LIT\")),block([declarationStatement(variables([],simpleType(id(\"TYPE\")),[variable(id(\"ID\"),[],methodCall([],id(\"ID\"),[number(\"LIT\")]))])),declarationStatement(variables([],simpleType(id(\"TYPE\")),[variable(id(\"ID\"),[],methodCall([],id(\"ID\"),[number(\"LIT\")]))])),expressionStatement(methodCall(id(\"ID\"),[],id(\"ID\"),[plus(stringLiteral(\"STR\"),id(\"ID\"))])),expressionStatement(assignment(id(\"ID\"),\"+=\",id(\"ID\"))),expressionStatement(assignment(id(\"ID\"),\"+=\",id(\"ID\")))]))-100-109",
      "name": "ASTClone_100_109"
    },
    {
      "locations": [
        {
          "filePath": "src/main/java/com/example/combat/BattleSimulator.java",
          "startLine": 26,
          "endLine": 37
        },
        {
          "filePath": "src/main/java/com/example/combat/BattleSimulator.java",
          "startLine": 39,
          "endLine": 49
        }
      ],
      "fragmentLength": 12,
      "cloneType": 3,
      "_id": "method([private()],[],simpleType(id(\"TYPE\")),id(\"ID\"),[parameter([],simpleType(id(\"TYPE\")),id(\"ID\"),[])],[],block([declarationStatement(variables([],simpleType(id(\"TYPE\")),[variable(id(\"ID\"),[],times(id(\"ID\"),number(\"LIT\")))])),declarationStatement(variables([],simpleType(id(\"TYPE\")),[variable(id(\"ID\"),[],minus(methodCall(id(\"ID\"),[],id(\"ID\"),[number(\"LIT\")]),number(\"LIT\")))])),declarationStatement(variables([],simpleType(id(\"TYPE\")),[variable(id(\"ID\"),[],plus(id(\"ID\"),id(\"ID\")))])),return(methodCall(id(\"ID\"),[],id(\"ID\"),[number(\"LIT\"),id(\"ID\")]))]))-26-39",
      "name": "ASTClone_26_39"
    }
  ]
}